boltz_mcp/__init__.py
boltz_mcp/cli.py
boltz_mcp/server.py
boltz_mcp-0.1.2.dist-info/METADATA
boltz_mcp-0.1.2.dist-info/WHEEL
boltz_mcp-0.1.2.dist-info/entry_points.txt
boltz_mcp-0.1.2.dist-info/licenses/LICENSE
boltz_mcp-0.1.2.dist-info/RECORD
