Metadata-Version: 2.4
Name: boltz-mcp
Version: 0.1.2
Summary: MCP for Boltz-2 model inference
Author-email: antonkulaga <antonkulaga@gmail.com>
License-File: LICENSE
Requires-Python: <3.13,>=3.11
Requires-Dist: biopython>=1.84
Requires-Dist: boltz>=2.1.1
Requires-Dist: eliot>=1.17.5
Requires-Dist: fastapi>=0.115.13
Requires-Dist: fastmcp>=2.9.2
Requires-Dist: gemmi>=0.6.5
Requires-Dist: pandas>=2.3.0
Requires-Dist: pycomfort>=0.0.18
Requires-Dist: pyyaml>=6.0.2
Requires-Dist: rdkit>=2025.3.3
Requires-Dist: requests==2.32.3
Requires-Dist: scipy>=1.13.1
Requires-Dist: torch>=2.7.0
Requires-Dist: tqdm>=4.67.1
Requires-Dist: triton==3.3.0
Requires-Dist: typer>=0.16.0
